<?xml version="1.0" ?>
<llsd>
<map>
    <key>package_description</key>
    <map>
      <key>copyright</key>
      <string>Copyright 2008, Google Inc.</string>
      <key>description</key>
      <string>a library for writing and using C++ mock classes</string>
      <key>license</key>
      <string>BSD</string>
      <key>license_file</key>
      <string>LICENSES/COPYING</string>
      <key>name</key>
      <string>gmock</string>
      <key>version</key>
      <string>1.5.0</string>
    </map>
    <key>type</key>
    <string>autobuild</string>
    <key>version</key>
    <string>1.2</string>
  </map>
</llsd>
